pooldose/__init__.py
pooldose/__main__.py
pooldose/client.py
pooldose/constants.py
pooldose/device_analyzer.py
pooldose/mock_client.py
pooldose/py.typed
pooldose/request_handler.py
pooldose/request_status.py
pooldose/type_definitions.py
pooldose/mappings/__init__.py
pooldose/mappings/mapping_info.py
pooldose/mappings/model_PDPR1H1HAR1V0_FW539224.json
pooldose/mappings/model_PDPR1H1HAW100_FW539187.json
pooldose/values/__init__.py
pooldose/values/instant_values.py
pooldose/values/static_values.py
python_pooldose-0.7.0.dist-info/licenses/LICENSE
python_pooldose-0.7.0.dist-info/METADATA
python_pooldose-0.7.0.dist-info/WHEEL
python_pooldose-0.7.0.dist-info/entry_points.txt
python_pooldose-0.7.0.dist-info/top_level.txt
python_pooldose-0.7.0.dist-info/RECORD
