Metadata-Version: 2.4
Name: python-pooldose
Version: 0.7.0
Summary: Unoffical async Python client for SEKO PoolDose devices
Author-email: Lukas Maertin <pypi@lukas-maertin.de>
License-Expression: MIT
Project-URL: Homepage, https://github.com/lmaertin/python-pooldose
Project-URL: Repository, https://github.com/lmaertin/python-pooldose
Requires-Python: >=3.11
License-File: LICENSE
Requires-Dist: aiohttp
Requires-Dist: aiofiles
Requires-Dist: getmac
Provides-Extra: dev
Requires-Dist: pytest; extra == "dev"
Requires-Dist: pytest-asyncio; extra == "dev"
Dynamic: license-file
